pymove/__init__.py
pymove/core/__init__.py
pymove/core/dask.py
pymove/core/dataframe.py
pymove/core/grid.py
pymove/core/interface.py
pymove/core/pandas.py
pymove/core/pandas_discrete.py
pymove/models/__init__.py
pymove/models/anomaly_detection.py
pymove/models/classification.py
pymove/models/pattern_mining/__init__.py
pymove/models/pattern_mining/clustering.py
pymove/models/pattern_mining/freq_seq_patterns.py
pymove/models/pattern_mining/moving_together_patterns.py
pymove/models/pattern_mining/periodic_patterns.py
pymove/preprocessing/__init__.py
pymove/preprocessing/compression.py
pymove/preprocessing/filters.py
pymove/preprocessing/segmentation.py
pymove/preprocessing/stay_point_detection.py
pymove/query/__init__.py
pymove/query/query.py
pymove/semantic/__init__.py
pymove/semantic/semantic.py
pymove/tests/__init__.py
pymove/tests/test_base_init.py
pymove/tests/test_core_dask.py
pymove/tests/test_core_dataframe.py
pymove/tests/test_core_grid.py
pymove/tests/test_core_pandas.py
pymove/tests/test_core_pandas_discrete.py
pymove/tests/test_models_pattern_mining_clustering.py
pymove/tests/test_preprocessing_compression.py
pymove/tests/test_preprocessing_filters.py
pymove/tests/test_preprocessing_segmentation.py
pymove/tests/test_preprocessing_stay_point_detection.py
pymove/tests/test_query.py
pymove/tests/test_semantic.py
pymove/tests/test_utils_conversions.py
pymove/tests/test_utils_data_augmentation.py
pymove/tests/test_utils_datetime.py
pymove/tests/test_utils_distances.py
pymove/tests/test_utils_geoutils.py
pymove/tests/test_utils_integration.py
pymove/tests/test_utils_math.py
pymove/tests/test_utils_mem.py
pymove/tests/test_utils_networkx.py
pymove/tests/test_utils_trajectories.py
pymove/tests/test_utils_visual.py
pymove/tests/test_visualization_folium.py
pymove/tests/test_visualization_matplotlib.py
pymove/tests/baseline/features.png
pymove/tests/baseline/plot_bounds.png
pymove/tests/baseline/plot_coords.png
pymove/tests/baseline/plot_line.png
pymove-3.0.1.dist-info/LICENSE
pymove-3.0.1.dist-info/METADATA
pymove-3.0.1.dist-info/WHEEL
pymove-3.0.1.dist-info/top_level.txt
pymove-3.0.1.dist-info/RECORD
