Metadata-Version: 2.1
Name: pymove
Version: 3.0.1
Summary: A lib python to processing and visualization of trajectories and other spatial-temporal data
Home-page: https://github.com/InsightLab/PyMove
Author: Insight Data Science Lab
Author-email: insightlab@dc.ufc.br
License: MIT
Platform: UNKNOWN
Classifier: Development Status :: 5 - Production/Stable
Classifier: Programming Language :: Python :: 3
Classifier: License :: OSI Approved :: MIT License
Classifier: Operating System :: OS Independent
Classifier: Typing :: Typed
Requires-Python: >=3.6
Requires-Dist: branca
Requires-Dist: dask[dataframe]
Requires-Dist: folium (>=0.10.1)
Requires-Dist: geohash2
Requires-Dist: geojson
Requires-Dist: holidays
Requires-Dist: IPython
Requires-Dist: ipywidgets
Requires-Dist: joblib
Requires-Dist: matplotlib
Requires-Dist: mplleaflet
Requires-Dist: networkx
Requires-Dist: numpy
Requires-Dist: pandas (<1.4.0,>=1.1.0)
Requires-Dist: psutil
Requires-Dist: python-dateutil
Requires-Dist: pytz
Requires-Dist: scikit-learn
Requires-Dist: scipy
Requires-Dist: shapely
Requires-Dist: tqdm
